{
  "round": 1,
  "summary": {
    "total_findings": 4,
    "new_findings": 4,
    "updated_existing_findings": 0,
    "rejected_candidates": 8,
    "action_counts": {
      "rewritten_agent_signal": 4
    },
    "rejection_reason_counts": {
      "other": 8
    }
  },
  "findings": [
    {
      "id": "F-001",
      "action": "rewritten_agent_signal",
      "severity": "Critical",
      "confidence": "high",
      "title": "Batched ETH commitments can reuse one `msg.value` multiple times",
      "source_agents": [
        "codex_1"
      ],
      "best_agent_match": {
        "agent": "codex_1",
        "title": "Batched ETH bids can reuse a single `msg.value` to mint multiple commitments",
        "score": 0.757
      },
      "locations": [
        "0x4c4564a1fe775d97297f9e3dc2e762e0ed5dda0e/contracts/Utils/BoringBatchable.sol:35",
        "0x4c4564a1fe775d97297f9e3dc2e762e0ed5dda0e/contracts/Auctions/DutchAuction.sol:263",
        "0x4c4564a1fe775d97297f9e3dc2e762e0ed5dda0e/contracts/Auctions/DutchAuction.sol:274",
        "0x4c4564a1fe775d97297f9e3dc2e762e0ed5dda0e/contracts/Auctions/DutchAuction.sol:279",
        "0x4c4564a1fe775d97297f9e3dc2e762e0ed5dda0e/contracts/Auctions/DutchAuction.sol:510",
        "0x4c4564a1fe775d97297f9e3dc2e762e0ed5dda0e/contracts/Auctions/DutchAuction.sol:512"
      ]
    },
    {
      "id": "F-002",
      "action": "rewritten_agent_signal",
      "severity": "High",
      "confidence": "medium",
      "title": "Anyone can front-run initialization of an uninitialized auction and seize admin/proceeds control",
      "source_agents": [
        "codex_1",
        "opencode_1"
      ],
      "best_agent_match": {
        "agent": "codex_1",
        "title": "Any first caller can initialize an uninitialized auction and seize admin and wallet control",
        "score": 0.727
      },
      "locations": [
        "0x4c4564a1fe775d97297f9e3dc2e762e0ed5dda0e/contracts/Access/MISOAdminAccess.sol:31",
        "0x4c4564a1fe775d97297f9e3dc2e762e0ed5dda0e/contracts/Auctions/DutchAuction.sol:138",
        "0x4c4564a1fe775d97297f9e3dc2e762e0ed5dda0e/contracts/Auctions/DutchAuction.sol:176",
        "0x4c4564a1fe775d97297f9e3dc2e762e0ed5dda0e/contracts/Auctions/DutchAuction.sol:179",
        "0x4c4564a1fe775d97297f9e3dc2e762e0ed5dda0e/contracts/Auctions/DutchAuction.sol:448",
        "0x4c4564a1fe775d97297f9e3dc2e762e0ed5dda0e/contracts/Auctions/DutchAuction.sol:629"
      ]
    },
    {
      "id": "F-003",
      "action": "rewritten_agent_signal",
      "severity": "Medium",
      "confidence": "medium",
      "title": "The auction accounts for nominal transfer amounts instead of actual tokens received",
      "source_agents": [
        "codex_1"
      ],
      "best_agent_match": {
        "agent": "codex_1",
        "title": "The auction books nominal token amounts instead of actual received amounts",
        "score": 0.764
      },
      "locations": [
        "0x4c4564a1fe775d97297f9e3dc2e762e0ed5dda0e/contracts/Auctions/DutchAuction.sol:167",
        "0x4c4564a1fe775d97297f9e3dc2e762e0ed5dda0e/contracts/Auctions/DutchAuction.sol:179",
        "0x4c4564a1fe775d97297f9e3dc2e762e0ed5dda0e/contracts/Auctions/DutchAuction.sol:313",
        "0x4c4564a1fe775d97297f9e3dc2e762e0ed5dda0e/contracts/Auctions/DutchAuction.sol:315",
        "0x4c4564a1fe775d97297f9e3dc2e762e0ed5dda0e/contracts/Auctions/DutchAuction.sol:316",
        "0x4c4564a1fe775d97297f9e3dc2e762e0ed5dda0e/contracts/Auctions/DutchAuction.sol:341",
        "0x4c4564a1fe775d97297f9e3dc2e762e0ed5dda0e/contracts/Auctions/DutchAuction.sol:343"
      ]
    },
    {
      "id": "F-004",
      "action": "rewritten_agent_signal",
      "severity": "Medium",
      "confidence": "medium",
      "title": "Admin can redirect auction proceeds after users have already committed",
      "source_agents": [
        "opencode_1"
      ],
      "best_agent_match": {
        "agent": "opencode_1",
        "title": "Arbitrary wallet change after auction commitments",
        "score": 0.403
      },
      "locations": [
        "0x4c4564a1fe775d97297f9e3dc2e762e0ed5dda0e/contracts/Auctions/DutchAuction.sol:113",
        "0x4c4564a1fe775d97297f9e3dc2e762e0ed5dda0e/contracts/Auctions/DutchAuction.sol:463",
        "0x4c4564a1fe775d97297f9e3dc2e762e0ed5dda0e/contracts/Auctions/DutchAuction.sol:476",
        "0x4c4564a1fe775d97297f9e3dc2e762e0ed5dda0e/contracts/Auctions/DutchAuction.sol:606",
        "0x4c4564a1fe775d97297f9e3dc2e762e0ed5dda0e/contracts/Auctions/DutchAuction.sol:610"
      ]
    }
  ],
  "rejected_candidates": [
    {
      "title": "Inconsistent use of nonReentrant modifier",
      "source_agents": [
        "opencode_1"
      ],
      "reason_category": "other",
      "reason": "Generic pattern only; no concrete reentrant exploit is supported by the code, and the cited unguarded functions do not expose a realistic permissionless reentrancy path with protocol-level harm."
    },
    {
      "title": "Division by zero in price calculation functions",
      "source_agents": [
        "opencode_1"
      ],
      "reason_category": "other",
      "reason": "Initialized auctions enforce `_minimumPrice > 0` in both `initAuction()` and `setAuctionPrice()`, so `clearingPrice()` cannot be zero in the live configuration this contract permits."
    },
    {
      "title": "Deprecated Solidity version 0.6.12",
      "source_agents": [
        "opencode_1"
      ],
      "reason_category": "other",
      "reason": "Using an older compiler version is not, by itself, a concrete reportable vulnerability in this codebase."
    },
    {
      "title": "Outdated `.transfer()` pattern for ETH transfers",
      "source_agents": [
        "opencode_1"
      ],
      "reason_category": "other",
      "reason": "The cited `_tokenPayment()` helper is unused; live ETH payouts use `_safeTransferETH`, and the direct `transfer` in `commitEth()` only refunds the caller-chosen beneficiary within the same transaction."
    },
    {
      "title": "Comment and code discrepancy for finalizeTimeExpired",
      "source_agents": [
        "opencode_1"
      ],
      "reason_category": "other",
      "reason": "Documentation mismatch only; it does not create a realistic exploit or protocol-level harm."
    },
    {
      "title": "Wallet address can trigger finalization",
      "source_agents": [
        "opencode_1"
      ],
      "reason_category": "other",
      "reason": "Allowing the configured payout wallet to finalize does not bypass the existing success/timeout conditions and does not by itself create a theft or insolvency vector."
    },
    {
      "title": "IERC20 interface requires permit which many tokens lack",
      "source_agents": [
        "opencode_1"
      ],
      "reason_category": "other",
      "reason": "`permitToken()` is an optional helper; calling it against a token without `permit()` only reverts that caller's own transaction and does not endanger auction funds or state."
    },
    {
      "title": "Missing validation for pointList contract",
      "source_agents": [
        "opencode_1"
      ],
      "reason_category": "other",
      "reason": "This is an admin-only misconfiguration risk; the admin already controls whether the point list is enabled, so no permissionless exploit or unexpected asset loss is shown."
    }
  ]
}
