{"_format":"","paths":{"artifacts":"out","build_infos":"out/build-info","sources":"FlawVerifier.sol","tests":"test","scripts":"script","libraries":[]},"files":{"FlawVerifier.sol":{"lastModificationDate":1779025847545,"contentHash":"742d50cd365257e9","interfaceReprHash":null,"sourceName":"FlawVerifier.sol","imports":[],"versionRequirement":"^0.8.20","artifacts":{"FlawVerifier":{"0.8.30":{"default":{"path":"FlawVerifier.sol/FlawVerifier.json","build_id":"1a0c4180683acd0a"}}},"IERC20Like":{"0.8.30":{"default":{"path":"FlawVerifier.sol/IERC20Like.json","build_id":"1a0c4180683acd0a"}}},"IERC20MetadataLike":{"0.8.30":{"default":{"path":"FlawVerifier.sol/IERC20MetadataLike.json","build_id":"1a0c4180683acd0a"}}},"IFlashLoanRecipientLike":{"0.8.30":{"default":{"path":"FlawVerifier.sol/IFlashLoanRecipientLike.json","build_id":"1a0c4180683acd0a"}}},"IIndexToken":{"0.8.30":{"default":{"path":"FlawVerifier.sol/IIndexToken.json","build_id":"1a0c4180683acd0a"}}},"IStakingPoolTokenLike":{"0.8.30":{"default":{"path":"FlawVerifier.sol/IStakingPoolTokenLike.json","build_id":"1a0c4180683acd0a"}}},"IUniswapV2CalleeLike":{"0.8.30":{"default":{"path":"FlawVerifier.sol/IUniswapV2CalleeLike.json","build_id":"1a0c4180683acd0a"}}},"IUniswapV2FactoryLike":{"0.8.30":{"default":{"path":"FlawVerifier.sol/IUniswapV2FactoryLike.json","build_id":"1a0c4180683acd0a"}}},"IUniswapV2PairLike":{"0.8.30":{"default":{"path":"FlawVerifier.sol/IUniswapV2PairLike.json","build_id":"1a0c4180683acd0a"}}}},"seenByCompiler":true}},"builds":["1a0c4180683acd0a"],"profiles":{"default":{"solc":{"optimizer":{"enabled":false,"runs":200},"metadata":{"useLiteralContent":false,"bytecodeHash":"ipfs","appendCBOR":true},"outputSelection":{"*":{"*":["abi","evm.bytecode.object","evm.bytecode.sourceMap","evm.bytecode.linkReferences","evm.deployedBytecode.object","evm.deployedBytecode.sourceMap","evm.deployedBytecode.linkReferences","evm.deployedBytecode.immutableReferences","evm.methodIdentifiers","metadata"]}},"evmVersion":"shanghai","viaIR":false,"libraries":{}},"vyper":{"evmVersion":"shanghai","outputSelection":{"*":{"*":["abi","evm.bytecode","evm.deployedBytecode"]}}}}},"preprocessed":false,"mocks":[]}