{
  "round": 1,
  "summary": {
    "total_findings": 3,
    "new_findings": 3,
    "updated_existing_findings": 0,
    "rejected_candidates": 7,
    "action_counts": {
      "exact_agent_candidate": 3
    },
    "rejection_reason_counts": {
      "factually_incorrect": 1,
      "other": 6
    }
  },
  "findings": [
    {
      "id": "F-001",
      "action": "exact_agent_candidate",
      "severity": "Critical",
      "confidence": "high",
      "title": "Swap invariant is weakened by a 100x scaling mismatch, allowing near-total reserve drains",
      "source_agents": [
        "codex_1"
      ],
      "best_agent_match": {
        "agent": "codex_1",
        "title": "Swap invariant is weakened by a 100x scaling mismatch, allowing near-total reserve drains",
        "score": 1.0
      },
      "locations": [
        "0xa0ff0e694275023f4986dc3ca12a6eb5d6056c62/Contract.sol:403",
        "0xa0ff0e694275023f4986dc3ca12a6eb5d6056c62/Contract.sol:404",
        "0xa0ff0e694275023f4986dc3ca12a6eb5d6056c62/Contract.sol:405"
      ]
    },
    {
      "id": "F-002",
      "action": "exact_agent_candidate",
      "severity": "High",
      "confidence": "high",
      "title": "Referral fee transfers are excluded from reserve accounting, corrupting reserves after swaps",
      "source_agents": [
        "codex_1"
      ],
      "best_agent_match": {
        "agent": "codex_1",
        "title": "Referral fee transfers are excluded from reserve accounting, corrupting reserves after every swap",
        "score": 0.963
      },
      "locations": [
        "0xa0ff0e694275023f4986dc3ca12a6eb5d6056c62/Contract.sol:379",
        "0xa0ff0e694275023f4986dc3ca12a6eb5d6056c62/Contract.sol:380",
        "0xa0ff0e694275023f4986dc3ca12a6eb5d6056c62/Contract.sol:391",
        "0xa0ff0e694275023f4986dc3ca12a6eb5d6056c62/Contract.sol:397",
        "0xa0ff0e694275023f4986dc3ca12a6eb5d6056c62/Contract.sol:408",
        "0xa0ff0e694275023f4986dc3ca12a6eb5d6056c62/Contract.sol:320",
        "0xa0ff0e694275023f4986dc3ca12a6eb5d6056c62/Contract.sol:321",
        "0xa0ff0e694275023f4986dc3ca12a6eb5d6056c62/Contract.sol:416",
        "0xa0ff0e694275023f4986dc3ca12a6eb5d6056c62/Contract.sol:417"
      ]
    },
    {
      "id": "F-003",
      "action": "exact_agent_candidate",
      "severity": "Medium",
      "confidence": "low",
      "title": "Referral rewards are attributed to a caller-controlled `to` address, enabling likely self-referral farming",
      "source_agents": [
        "codex_1"
      ],
      "best_agent_match": {
        "agent": "codex_1",
        "title": "Referral rewards are attributed to the user-controlled `to` address, enabling likely self-referral farming",
        "score": 0.953
      },
      "locations": [
        "0xa0ff0e694275023f4986dc3ca12a6eb5d6056c62/Contract.sol:375",
        "0xa0ff0e694275023f4986dc3ca12a6eb5d6056c62/Contract.sol:392",
        "0xa0ff0e694275023f4986dc3ca12a6eb5d6056c62/Contract.sol:398"
      ]
    }
  ],
  "rejected_candidates": [
    {
      "title": "Reentrancy via callback before K invariant validation",
      "source_agents": [
        "opencode_1"
      ],
      "reason_category": "other",
      "reason": "`swap()` is protected by the `lock` modifier, so reentrant calls into the pair's state-changing entrypoints revert. Calling `NimbusCall` before the invariant check is the standard flash-swap pattern and is not by itself an exploitable reentrancy bug here."
    },
    {
      "title": "Unvalidated referral program can steal user funds",
      "source_agents": [
        "opencode_1"
      ],
      "reason_category": "factually_incorrect",
      "reason": "The referral program address is a trusted factory-controlled dependency, not a permissionless attack surface. Also, receiving ERC20 transfers does not invoke a recipient fallback, so the stated fallback-based theft path is incorrect."
    },
    {
      "title": "Arbitrary external call enables flash loan attacks",
      "source_agents": [
        "opencode_1"
      ],
      "reason_category": "other",
      "reason": "Allowing a callback to `to` is the normal flash-swap mechanism for Uniswap V2-style pairs, not a standalone vulnerability. Profitability still depends on external market conditions, not a flaw in this contract."
    },
    {
      "title": "Referral fees transferred before K validation",
      "source_agents": [
        "opencode_1"
      ],
      "reason_category": "other",
      "reason": "If the later `require` fails, the whole transaction reverts, including the ERC20 transfers and `recordFee()` call. The fees are not permanently lost on a reverted swap."
    },
    {
      "title": "No slippage protection allows unlimited slippage",
      "source_agents": [
        "opencode_1"
      ],
      "reason_category": "other",
      "reason": "This pair is a low-level AMM primitive. Slippage protection is normally enforced by routers or callers, so the absence of min-out parameters in the pair itself is not reportable."
    },
    {
      "title": "Permissionless skim and sync functions",
      "source_agents": [
        "opencode_1"
      ],
      "reason_category": "other",
      "reason": "These functions are standard for Uniswap V2-style pairs. `skim()` only transfers excess balances above reserves, and `sync()` only aligns reserves to actual balances; neither creates a realistic standalone exploit here."
    },
    {
      "title": "Unusual referral fee denominator",
      "source_agents": [
        "opencode_1"
      ],
      "reason_category": "other",
      "reason": "Using `1994` is unusual but plausibly intentional to approximate a 0.15% referral charge. On its own this is not evidence of an exploitable bug or meaningful protocol harm."
    }
  ]
}
